dgctl/__init__.py
dgctl/aws.py
dgctl/commands.py
dgctl/dgctl.py
dgctl/utils.py
dgctl-0.0.4.dist-info/entry_points.txt
dgctl-0.0.4.dist-info/LICENSE
dgctl-0.0.4.dist-info/WHEEL
dgctl-0.0.4.dist-info/METADATA
dgctl-0.0.4.dist-info/RECORD
