Metadata-Version: 2.1
Name: dgctl
Version: 0.0.4
Summary: digger.dev client
Author: Mohammed Habib
Author-email: mo@digger.dev
Requires-Python: >=3.7,<4.0
Classifier: Programming Language :: Python :: 3
Classifier: Programming Language :: Python :: 3.7
Classifier: Programming Language :: Python :: 3.8
Classifier: Programming Language :: Python :: 3.9
Classifier: Programming Language :: Python :: 3.10
Classifier: Programming Language :: Python :: 3.11
Requires-Dist: click (>=8.1.3,<9.0.0)
Requires-Dist: python-dotenv (>=0.0.0)
